parrot/__init__.py
parrot/config/__init__.py
parrot/config/config.py
parrot/example/__init__.py
parrot/example/example.ipynb
parrot/example/example_compact.ipynb
parrot/example/example_compact.py
parrot/example/init.py
parrot/example/example_data/__init__.py
parrot/load/__init__.py
parrot/load/load.py
parrot/load/recording_device.py
parrot/load/recording_type.py
parrot/plot/__init__.py
parrot/plot/plot.py
parrot/plot/plot_debug.py
parrot/plot/h2o/WaterAbsorptionLines.csv
parrot/plot/h2o/__init__.py
parrot/process/__init__.py
parrot/process/post_process_data.py
parrot/process/prepare_data.py
parrot/process/process_data.py
parrot-0.1.10.dist-info/METADATA
parrot-0.1.10.dist-info/WHEEL
parrot-0.1.10.dist-info/licenses/LICENSE
parrot-0.1.10.dist-info/RECORD
