Metadata-Version: 2.3
Name: parrot
Version: 0.1.10
Summary: parrot is able to to process and average continuously recorded THz data.
Project-URL: Source, https://github.com/puls-lab/parrot
Project-URL: Documentation, https://puls-lab.github.io/parrot/
Author-email: Tim Vogel <32876663+TimVog@users.noreply.github.com>
License-Expression: GPL-3.0-or-later
License-File: LICENSE
Keywords: DR,SNR,THz,Terahertz,averaging,dataprocessing,dynamic range,signal-to-noise ratio
Classifier: License :: OSI Approved :: GNU Lesser General Public License v3 or later (LGPLv3+)
Classifier: Operating System :: OS Independent
Classifier: Programming Language :: Python
Classifier: Programming Language :: Python :: 3.9
Classifier: Programming Language :: Python :: 3.10
Classifier: Programming Language :: Python :: 3.11
Classifier: Programming Language :: Python :: 3.12
Requires-Python: >=3.9
Requires-Dist: colorama>=0.4.6
Requires-Dist: h5py
Requires-Dist: matplotlib
Requires-Dist: numpy
Requires-Dist: scipy
